flask_simple_tsdb/__init__.py
flask_simple_tsdb/flask_simple_tsdb.py
flask_simple_tsdb-2.1.3.0.dist-info/METADATA
flask_simple_tsdb-2.1.3.0.dist-info/WHEEL
flask_simple_tsdb-2.1.3.0.dist-info/top_level.txt
flask_simple_tsdb-2.1.3.0.dist-info/RECORD
